{
  "LOGIN": {
    "LOGIN_BUTTON": {
      "ACTIVE": "Осуществляется вход",
      "TEXT": "Войти"
    },
    "NEW": "Еще не зарегистрированы на SimpleSite? Зарегистрироваться",
    "PASSWORD": {
      "LABEL": "Пароль",
      "MAXLENGTH": "Ваш пароль слишком длинный",
      "MINLENGTH": "Ваш пароль слишком короткий",
      "REQUIRED": "Не забудьте указать пароль"
    },
    "SORRY": "Вход не выполнен. Проверьте правильность указанного имени пользователя и пароля",
    "TITLE": "Войти",
    "USERNAME": {
      "LABEL": "Имя пользователя",
      "REQUIRED": "Сообщите нам ваше имя пользователя"
    }
  }
}